{
    "dataset_name": "test",
    "table_name": "imdb_top_1000_speed_test",
    "header": [
      "Series_Title",
      "Released_Year",
      "Runtime (min)",
      "Genre",
      "IMDB_Rating",
      "Overview",
      "Meta_score",
      "Director",
      "Star1",
      "No_of_Votes",
      "Gross"
    ],
    "total_rows": 25,
    "classified_columns": {
      "NE": {
        "0": "OTHER",
        "7": "PERSON",
        "8": "PERSON"
      },
      "LIT": {
        "1": "NUMBER",
        "2": "NUMBER",
        "3": "STRING",
        "4": "NUMBER",
        "5": "STRING",
        "6": "NUMBER",
        "9": "NUMBER",
        "10": "NUMBER"
      }
    },
    "data": [
      {
        "Series_Title": "The Shawshank Redemption",
        "Released_Year": "1994",
        "Runtime (min)": 142,
        "Genre": "Drama",
        "IMDB_Rating": 9.3,
        "Overview": "Two imprisoned men bond over a number of years, finding solace and eventual redemption through acts of common decency.",
        "Meta_score": 80.0,
        "Director": "Frank Darabont",
        "Star1": "Tim Robbins",
        "No_of_Votes": 2343110,
        "Gross": "28,341,469"
      },
      {
        "Series_Title": "The Godfather",
        "Released_Year": "1972",
        "Runtime (min)": 175,
        "Genre": "Crime, Drama",
        "IMDB_Rating": 9.2,
        "Overview": "An organized crime dynasty's aging patriarch transfers control of his clandestine empire to his reluctant son.",
        "Meta_score": 100.0,
        "Director": "Francis Ford Coppola",
        "Star1": "Marlon Brando",
        "No_of_Votes": 1620367,
        "Gross": "134,966,411"
      },
      {
        "Series_Title": "The Dark Knight",
        "Released_Year": "2008",
        "Runtime (min)": 152,
        "Genre": "Action, Crime, Drama",
        "IMDB_Rating": 9.0,
        "Overview": "When the menace known as the Joker wreaks havoc and chaos on the people of Gotham, Batman must accept one of the greatest psychological and physical tests of his ability to fight injustice.",
        "Meta_score": 84.0,
        "Director": "Christopher Nolan",
        "Star1": "Christian Bale",
        "No_of_Votes": 2303232,
        "Gross": "534,858,444"
      },
      {
        "Series_Title": "The Godfather: Part II",
        "Released_Year": "1974",
        "Runtime (min)": 202,
        "Genre": "Crime, Drama",
        "IMDB_Rating": 9.0,
        "Overview": "The early life and career of Vito Corleone in 1920s New York City is portrayed, while his son, Michael, expands and tightens his grip on the family crime syndicate.",
        "Meta_score": 90.0,
        "Director": "Francis Ford Coppola",
        "Star1": "Al Pacino",
        "No_of_Votes": 1129952,
        "Gross": "57,300,000"
      },
      {
        "Series_Title": "12 Angry Men",
        "Released_Year": "1957",
        "Runtime (min)": 96,
        "Genre": "Crime, Drama",
        "IMDB_Rating": 9.0,
        "Overview": "A jury holdout attempts to prevent a miscarriage of justice by forcing his colleagues to reconsider the evidence.",
        "Meta_score": 96.0,
        "Director": "Sidney Lumet",
        "Star1": "Henry Fonda",
        "No_of_Votes": 689845,
        "Gross": "4,360,000"
      },
      {
        "Series_Title": "The Lord of the Rings: The Return of the King",
        "Released_Year": "2003",
        "Runtime (min)": 201,
        "Genre": "Action, Adventure, Drama",
        "IMDB_Rating": 8.9,
        "Overview": "Gandalf and Aragorn lead the World of Men against Sauron's army to draw his gaze from Frodo and Sam as they approach Mount Doom with the One Ring.",
        "Meta_score": 94.0,
        "Director": "Peter Jackson",
        "Star1": "Elijah Wood",
        "No_of_Votes": 1642758,
        "Gross": "377,845,905"
      },
      {
        "Series_Title": "Pulp Fiction",
        "Released_Year": "1994",
        "Runtime (min)": 154,
        "Genre": "Crime, Drama",
        "IMDB_Rating": 8.9,
        "Overview": "The lives of two mob hitmen, a boxer, a gangster and his wife, and a pair of diner bandits intertwine in four tales of violence and redemption.",
        "Meta_score": 94.0,
        "Director": "Quentin Tarantino",
        "Star1": "John Travolta",
        "No_of_Votes": 1826188,
        "Gross": "107,928,762"
      },
      {
        "Series_Title": "Schindler's List",
        "Released_Year": "1993",
        "Runtime (min)": 195,
        "Genre": "Biography, Drama, History",
        "IMDB_Rating": 8.9,
        "Overview": "In German-occupied Poland during World War II, industrialist Oskar Schindler gradually becomes concerned for his Jewish workforce after witnessing their persecution by the Nazis.",
        "Meta_score": 94.0,
        "Director": "Steven Spielberg",
        "Star1": "Liam Neeson",
        "No_of_Votes": 1213505,
        "Gross": "96,898,818"
      },
      {
        "Series_Title": "Inception",
        "Released_Year": "2010",
        "Runtime (min)": 148,
        "Genre": "Action, Adventure, Sci-Fi",
        "IMDB_Rating": 8.8,
        "Overview": "A thief who steals corporate secrets through the use of dream-sharing technology is given the inverse task of planting an idea into the mind of a C.E.O.",
        "Meta_score": 74.0,
        "Director": "Christopher Nolan",
        "Star1": "Leonardo DiCaprio",
        "No_of_Votes": 2067042,
        "Gross": "292,576,195"
      },
      {
        "Series_Title": "Fight Club",
        "Released_Year": "1999",
        "Runtime (min)": 139,
        "Genre": "Drama",
        "IMDB_Rating": 8.8,
        "Overview": "An insomniac office worker and a devil-may-care soapmaker form an underground fight club that evolves into something much, much more.",
        "Meta_score": 66.0,
        "Director": "David Fincher",
        "Star1": "Brad Pitt",
        "No_of_Votes": 1854740,
        "Gross": "37,030,102"
      },
      {
        "Series_Title": "The Lord of the Rings: The Fellowship of the Ring",
        "Released_Year": "2001",
        "Runtime (min)": 178,
        "Genre": "Action, Adventure, Drama",
        "IMDB_Rating": 8.8,
        "Overview": "A meek Hobbit from the Shire and eight companions set out on a journey to destroy the powerful One Ring and save Middle-earth from the Dark Lord Sauron.",
        "Meta_score": 92.0,
        "Director": "Peter Jackson",
        "Star1": "Elijah Wood",
        "No_of_Votes": 1661481,
        "Gross": "315,544,750"
      },
      {
        "Series_Title": "Forrest Gump",
        "Released_Year": "1994",
        "Runtime (min)": 142,
        "Genre": "Drama, Romance",
        "IMDB_Rating": 8.8,
        "Overview": "The presidencies of Kennedy and Johnson, the events of Vietnam, Watergate and other historical events unfold through the perspective of an Alabama man with an IQ of 75, whose only desire is to be reunited with his childhood sweetheart.",
        "Meta_score": 82.0,
        "Director": "Robert Zemeckis",
        "Star1": "Tom Hanks",
        "No_of_Votes": 1809221,
        "Gross": "330,252,182"
      },
      {
        "Series_Title": "Il buono, il brutto, il cattivo",
        "Released_Year": "1966",
        "Runtime (min)": 161,
        "Genre": "Western",
        "IMDB_Rating": 8.8,
        "Overview": "A bounty hunting scam joins two men in an uneasy alliance against a third in a race to find a fortune in gold buried in a remote cemetery.",
        "Meta_score": 90.0,
        "Director": "Sergio Leone",
        "Star1": "Clint Eastwood",
        "No_of_Votes": 688390,
        "Gross": "6,100,000"
      },
      {
        "Series_Title": "The Lord of the Rings: The Two Towers",
        "Released_Year": "2002",
        "Runtime (min)": 179,
        "Genre": "Action, Adventure, Drama",
        "IMDB_Rating": 8.7,
        "Overview": "While Frodo and Sam edge closer to Mordor with the help of the shifty Gollum, the divided fellowship makes a stand against Sauron's new ally, Saruman, and his hordes of Isengard.",
        "Meta_score": 87.0,
        "Director": "Peter Jackson",
        "Star1": "Elijah Wood",
        "No_of_Votes": 1485555,
        "Gross": "342,551,365"
      },
      {
        "Series_Title": "The Matrix",
        "Released_Year": "1999",
        "Runtime (min)": 136,
        "Genre": "Action, Sci-Fi",
        "IMDB_Rating": 8.7,
        "Overview": "When a beautiful stranger leads computer hacker Neo to a forbidding underworld, he discovers the shocking truth--the life he knows is the elaborate deception of an evil cyber-intelligence.",
        "Meta_score": 73.0,
        "Director": "Lana Wachowski",
        "Star1": "Lilly Wachowski",
        "No_of_Votes": 1676426,
        "Gross": "171,479,930"
      },
      {
        "Series_Title": "Goodfellas",
        "Released_Year": "1990",
        "Runtime (min)": 146,
        "Genre": "Biography, Crime, Drama",
        "IMDB_Rating": 8.7,
        "Overview": "The story of Henry Hill and his life in the mob, covering his relationship with his wife Karen Hill and his mob partners Jimmy Conway and Tommy DeVito in the Italian-American crime syndicate.",
        "Meta_score": 90.0,
        "Director": "Martin Scorsese",
        "Star1": "Robert De Niro",
        "No_of_Votes": 1020727,
        "Gross": "46,836,394"
      },
      {
        "Series_Title": "Star Wars: Episode V - The Empire Strikes Back",
        "Released_Year": "1980",
        "Runtime (min)": 124,
        "Genre": "Action, Adventure, Fantasy",
        "IMDB_Rating": 8.7,
        "Overview": "After the Rebels are brutally overpowered by the Empire on the ice planet Hoth, Luke Skywalker begins Jedi training with Yoda, while his friends are pursued by Darth Vader and a bounty hunter named Boba Fett all over the galaxy.",
        "Meta_score": 82.0,
        "Director": "Irvin Kershner",
        "Star1": "Mark Hamill",
        "No_of_Votes": 1159315,
        "Gross": "290,475,067"
      },
      {
        "Series_Title": "One Flew Over the Cuckoo's Nest",
        "Released_Year": "1975",
        "Runtime (min)": 133,
        "Genre": "Drama",
        "IMDB_Rating": 8.7,
        "Overview": "A criminal pleads insanity and is admitted to a mental institution, where he rebels against the oppressive nurse and rallies up the scared patients.",
        "Meta_score": 83.0,
        "Director": "Milos Forman",
        "Star1": "Jack Nicholson",
        "No_of_Votes": 918088,
        "Gross": "112,000,000"
      },
      {
        "Series_Title": "Hamilton",
        "Released_Year": "2020",
        "Runtime (min)": 160,
        "Genre": "Biography, Drama, History",
        "IMDB_Rating": 8.6,
        "Overview": "The real life of one of America's foremost founding fathers and first Secretary of the Treasury, Alexander Hamilton. Captured live on Broadway from the Richard Rodgers Theater with the original Broadway cast.",
        "Meta_score": 90.0,
        "Director": "Thomas Kail",
        "Star1": "Lin-Manuel Miranda",
        "No_of_Votes": 55291,
        "Gross": null
      },
      {
        "Series_Title": "Gisaengchung",
        "Released_Year": "2019",
        "Runtime (min)": 132,
        "Genre": "Comedy, Drama, Thriller",
        "IMDB_Rating": 8.6,
        "Overview": "Greed and class discrimination threaten the newly formed symbiotic relationship between the wealthy Park family and the destitute Kim clan.",
        "Meta_score": 96.0,
        "Director": "Bong Joon Ho",
        "Star1": "Kang-ho Song",
        "No_of_Votes": 552778,
        "Gross": "53,367,844"
      },
      {
        "Series_Title": "Soorarai Pottru",
        "Released_Year": "2020",
        "Runtime (min)": 153,
        "Genre": "Drama",
        "IMDB_Rating": 8.6,
        "Overview": "Nedumaaran Rajangam \"Maara\" sets out to make the common man fly and in the process takes on the world's most capital intensive industry and several enemies who stand in his way.",
        "Meta_score": null,
        "Director": "Sudha Kongara",
        "Star1": "Suriya",
        "No_of_Votes": 54995,
        "Gross": null
      },
      {
        "Series_Title": "Interstellar",
        "Released_Year": "2014",
        "Runtime (min)": 169,
        "Genre": "Adventure, Drama, Sci-Fi",
        "IMDB_Rating": 8.6,
        "Overview": "A team of explorers travel through a wormhole in space in an attempt to ensure humanity's survival.",
        "Meta_score": 74.0,
        "Director": "Christopher Nolan",
        "Star1": "Matthew McConaughey",
        "No_of_Votes": 1512360,
        "Gross": "188,020,017"
      },
      {
        "Series_Title": "Cidade de Deus",
        "Released_Year": "2002",
        "Runtime (min)": 130,
        "Genre": "Crime, Drama",
        "IMDB_Rating": 8.6,
        "Overview": "In the slums of Rio, two kids' paths diverge as one struggles to become a photographer and the other a kingpin.",
        "Meta_score": 79.0,
        "Director": "Fernando Meirelles",
        "Star1": "Kátia Lund",
        "No_of_Votes": 699256,
        "Gross": "7,563,397"
      },
      {
        "Series_Title": "Sen to Chihiro no kamikakushi",
        "Released_Year": "2001",
        "Runtime (min)": 125,
        "Genre": "Animation, Adventure, Family",
        "IMDB_Rating": 8.6,
        "Overview": "During her family's move to the suburbs, a sullen 10-year-old girl wanders into a world ruled by gods, witches, and spirits, and where humans are changed into beasts.",
        "Meta_score": 96.0,
        "Director": "Hayao Miyazaki",
        "Star1": "Daveigh Chase",
        "No_of_Votes": 651376,
        "Gross": "10,055,859"
      },
      {
        "Series_Title": "Avengers: Endgame",
        "Released_Year": "2019",
        "Runtime (min)": 181,
        "Genre": "Action, Adventure, Drama",
        "IMDB_Rating": 8.4,
        "Overview": "After the devastating events of Avengers: Infinity War (2018), the universe is in ruins. With the help of remaining allies, the Avengers assemble once more in order to reverse Thanos' actions and restore balance to the universe.",
        "Meta_score": 78.0,
        "Director": "Anthony Russo",
        "Star1": "Joe Russo",
        "No_of_Votes": 809955,
        "Gross": "858,373,000"
    }
    ]
  }